cmagick/__init__.py
cmagick/cmagick.py
cmagick/main.py
cmagick/test_cmagick.py
cmagick-0.1.4.dist-info/METADATA
cmagick-0.1.4.dist-info/WHEEL
cmagick-0.1.4.dist-info/entry_points.txt
cmagick-0.1.4.dist-info/top_level.txt
cmagick-0.1.4.dist-info/RECORD
