Metadata-Version: 2.1
Name: cmagick
Version: 0.1.4
Summary: An utility for converting and resizing images
Home-page: https://github.com/aissa-laribi/cmagick
Author: Aissa Laribi
Author-email: aissalaribi@yahoo.fr
License: MIT
